pydbase/__init__.py
pydbase/dbutils.py
pydbase/portalocker.py
pydbase/twinbase.py
pydbase/twinchain.py
pydbase/twincore.py
pydbase/docs/twinbase.html
pydbase/docs/twinchain.html
pydbase/docs/twincore.html
pydbase-1.7.1.data/scripts/chainadm.py
pydbase-1.7.1.data/scripts/dbaseadm.py
pydbase-1.7.1.dist-info/METADATA
pydbase-1.7.1.dist-info/WHEEL
pydbase-1.7.1.dist-info/entry_points.txt
pydbase-1.7.1.dist-info/top_level.txt
pydbase-1.7.1.dist-info/RECORD
