Metadata-Version: 2.1
Name: pydbase
Version: 1.7.1
Summary: High speed database with key / data in python.
Home-page: https://github.com/pglen/pydbase
Author: Peter Glen
Author-email: peterglen99@gmail.com
Classifier: Programming Language :: Python :: 3
Classifier: License :: OSI Approved :: MIT License
Classifier: Operating System :: OS Independent
Requires-Python: >=3
